{"sections":[],"primaryContentSections":[{"declarations":[{"tokens":[{"text":"@","kind":"attribute"},{"text":"MainActor","preciseIdentifier":"s:ScM","kind":"attribute"},{"text":" ","kind":"text"},{"text":"@preconcurrency","kind":"attribute"},{"text":" ","kind":"text"},{"text":"init","kind":"keyword"},{"text":"<","kind":"text"},{"text":"DestinationState","kind":"genericParameter"},{"text":", ","kind":"text"},{"text":"DestinationAction","kind":"genericParameter"},{"text":", ","kind":"text"},{"text":"IfContent","kind":"genericParameter"},{"text":", ","kind":"text"},{"text":"ElseContent","kind":"genericParameter"},{"text":">(","kind":"text"},{"text":"_","kind":"externalParam"},{"text":" ","kind":"text"},{"text":"store","kind":"internalParam"},{"text":": ","kind":"text"},{"text":"Store","preciseIdentifier":"s:22ComposableArchitecture5StoreC","kind":"typeIdentifier","identifier":"doc:\/\/ComposableArchitecture\/documentation\/ComposableArchitecture\/Store"},{"text":"<","kind":"text"},{"text":"PresentationState","preciseIdentifier":"s:22ComposableArchitecture17PresentationStateV","kind":"typeIdentifier","identifier":"doc:\/\/ComposableArchitecture\/documentation\/ComposableArchitecture\/PresentationState"},{"text":"<","kind":"text"},{"text":"DestinationState","kind":"typeIdentifier"},{"text":">, ","kind":"text"},{"text":"PresentationAction","preciseIdentifier":"s:22ComposableArchitecture18PresentationActionO","kind":"typeIdentifier","identifier":"doc:\/\/ComposableArchitecture\/documentation\/ComposableArchitecture\/PresentationAction"},{"text":"<","kind":"text"},{"text":"DestinationAction","kind":"typeIdentifier"},{"text":">>, ","kind":"text"},{"text":"state","kind":"externalParam"},{"text":" ","kind":"text"},{"text":"toState","kind":"internalParam"},{"text":": ","kind":"text"},{"text":"@escaping","kind":"keyword"},{"text":" (","kind":"text"},{"text":"DestinationState","kind":"typeIdentifier"},{"text":") -> ","kind":"text"},{"text":"State","kind":"typeIdentifier"},{"text":"?, ","kind":"text"},{"text":"action","kind":"externalParam"},{"text":" ","kind":"text"},{"text":"fromAction","kind":"internalParam"},{"text":": ","kind":"text"},{"text":"@escaping","kind":"keyword"},{"text":" (","kind":"text"},{"text":"Action","kind":"typeIdentifier"},{"text":") -> ","kind":"text"},{"text":"DestinationAction","kind":"typeIdentifier"},{"text":", ","kind":"text"},{"text":"@","kind":"attribute"},{"text":"ViewBuilder","preciseIdentifier":"s:7SwiftUI11ViewBuilderV","kind":"attribute"},{"text":" ","kind":"text"},{"text":"then","kind":"externalParam"},{"text":" ","kind":"text"},{"text":"ifContent","kind":"internalParam"},{"text":": ","kind":"text"},{"text":"@escaping","kind":"keyword"},{"text":" (","kind":"text"},{"text":"Store","preciseIdentifier":"s:22ComposableArchitecture5StoreC","kind":"typeIdentifier","identifier":"doc:\/\/ComposableArchitecture\/documentation\/ComposableArchitecture\/Store"},{"text":"<","kind":"text"},{"text":"State","kind":"typeIdentifier"},{"text":", ","kind":"text"},{"text":"Action","kind":"typeIdentifier"},{"text":">) -> ","kind":"text"},{"text":"IfContent","kind":"typeIdentifier"},{"text":", ","kind":"text"},{"text":"@","kind":"attribute"},{"text":"ViewBuilder","preciseIdentifier":"s:7SwiftUI11ViewBuilderV","kind":"attribute"},{"text":" ","kind":"text"},{"text":"else","kind":"externalParam"},{"text":" ","kind":"text"},{"text":"elseContent","kind":"internalParam"},{"text":": ","kind":"text"},{"text":"@escaping","kind":"keyword"},{"text":" () -> ","kind":"text"},{"text":"ElseContent","kind":"typeIdentifier"},{"text":") ","kind":"text"},{"text":"where","kind":"keyword"},{"text":" ","kind":"text"},{"text":"Content","kind":"typeIdentifier"},{"text":" == ","kind":"text"},{"text":"_ConditionalContent","kind":"typeIdentifier"},{"text":"<","kind":"text"},{"text":"IfContent","kind":"typeIdentifier"},{"text":", ","kind":"text"},{"text":"ElseContent","kind":"typeIdentifier"},{"text":">, ","kind":"text"},{"text":"IfContent","kind":"typeIdentifier"},{"text":" : ","kind":"text"},{"text":"View","preciseIdentifier":"s:7SwiftUI4ViewP","kind":"typeIdentifier"},{"text":", ","kind":"text"},{"text":"ElseContent","kind":"typeIdentifier"},{"text":" : ","kind":"text"},{"text":"View","preciseIdentifier":"s:7SwiftUI4ViewP","kind":"typeIdentifier"}],"platforms":["macOS"],"languages":["swift"]}],"kind":"declarations"},{"kind":"parameters","parameters":[{"content":[{"type":"paragraph","inlineContent":[{"type":"text","text":"A store of optional state."}]}],"name":"store"},{"content":[{"type":"paragraph","inlineContent":[{"type":"text","text":"A closure that attempts to extract state for the “if” branch from the destination"},{"type":"text","text":" "},{"type":"text","text":"state."}]}],"name":"toState"},{"content":[{"type":"paragraph","inlineContent":[{"type":"text","text":"A closure that embeds actions for the “if” branch in destination actions."}]}],"name":"fromAction"},{"content":[{"inlineContent":[{"text":"A function that is given a store of non-optional state and returns a view that","type":"text"},{"text":" ","type":"text"},{"text":"is visible only when the optional state is non-","type":"text"},{"code":"nil","type":"codeVoice"},{"text":" and state can be extracted from the","type":"text"},{"text":" ","type":"text"},{"text":"destination state.","type":"text"}],"type":"paragraph"}],"name":"ifContent"},{"content":[{"inlineContent":[{"text":"A view that is only visible when state cannot be extracted from the","type":"text"},{"text":" ","type":"text"},{"text":"destination.","type":"text"}],"type":"paragraph"}],"name":"elseContent"}]}],"kind":"symbol","abstract":[{"text":"Initializes an ","type":"text"},{"isActive":true,"type":"reference","identifier":"doc:\/\/ComposableArchitecture\/documentation\/ComposableArchitecture\/IfLetStore"},{"text":" view that computes content depending on if a store of","type":"text"},{"text":" ","type":"text"},{"isActive":true,"type":"reference","identifier":"doc:\/\/ComposableArchitecture\/documentation\/ComposableArchitecture\/PresentationState"},{"text":" and ","type":"text"},{"isActive":true,"type":"reference","identifier":"doc:\/\/ComposableArchitecture\/documentation\/ComposableArchitecture\/PresentationAction"},{"text":" is ","type":"text"},{"type":"codeVoice","code":"nil"},{"text":" or non-","type":"text"},{"type":"codeVoice","code":"nil"},{"text":" and state can further","type":"text"},{"text":" ","type":"text"},{"text":"be extracted from the destination state, ","type":"text"},{"inlineContent":[{"type":"text","text":"e.g."}],"type":"emphasis"},{"text":" it matches a particular case of an enum.","type":"text"}],"deprecationSummary":[{"inlineContent":[{"text":"Further scope the store into the 'state' and 'action' cases, instead. For more information, see the following article: https:\/\/pointfreeco.github.io\/swift-composable-architecture\/main\/documentation\/composablearchitecture\/migratingto1.5#Enum-driven-navigation-APIs","type":"text"}],"type":"paragraph"}],"identifier":{"interfaceLanguage":"swift","url":"doc:\/\/ComposableArchitecture\/documentation\/ComposableArchitecture\/IfLetStore\/init(_:state:action:then:else:)"},"metadata":{"platforms":[],"externalID":"s:22ComposableArchitecture10IfLetStoreV_5state6action4then4elseACyxq_7SwiftUI19_ConditionalContentVyqd_1_qd_2_GGAA0E0CyAA17PresentationStateVyqd__GAA0N6ActionOyqd_0_GG_xSgqd__cqd_0_q_cqd_1_ANyxq_Gcqd_2_yctcAKRs0_AH4ViewRd_1_AhXRd_2_r2_lufc","role":"symbol","title":"init(_:state:action:then:else:)","fragments":[{"text":"init","kind":"identifier"},{"text":"<","kind":"text"},{"text":"DestinationState","kind":"genericParameter"},{"text":", ","kind":"text"},{"text":"DestinationAction","kind":"genericParameter"},{"text":", ","kind":"text"},{"text":"IfContent","kind":"genericParameter"},{"text":", ","kind":"text"},{"text":"ElseContent","kind":"genericParameter"},{"text":">(","kind":"text"},{"preciseIdentifier":"s:22ComposableArchitecture5StoreC","text":"Store","kind":"typeIdentifier"},{"text":"<","kind":"text"},{"preciseIdentifier":"s:22ComposableArchitecture17PresentationStateV","text":"PresentationState","kind":"typeIdentifier"},{"text":"<","kind":"text"},{"text":"DestinationState","kind":"typeIdentifier"},{"text":">, ","kind":"text"},{"preciseIdentifier":"s:22ComposableArchitecture18PresentationActionO","text":"PresentationAction","kind":"typeIdentifier"},{"text":"<","kind":"text"},{"text":"DestinationAction","kind":"typeIdentifier"},{"text":">>, ","kind":"text"},{"text":"state","kind":"externalParam"},{"text":": (","kind":"text"},{"text":"DestinationState","kind":"typeIdentifier"},{"text":") -> ","kind":"text"},{"text":"State","kind":"typeIdentifier"},{"text":"?, ","kind":"text"},{"text":"action","kind":"externalParam"},{"text":": (","kind":"text"},{"text":"Action","kind":"typeIdentifier"},{"text":") -> ","kind":"text"},{"text":"DestinationAction","kind":"typeIdentifier"},{"text":", ","kind":"text"},{"text":"then","kind":"externalParam"},{"text":": (","kind":"text"},{"preciseIdentifier":"s:22ComposableArchitecture5StoreC","text":"Store","kind":"typeIdentifier"},{"text":"<","kind":"text"},{"text":"State","kind":"typeIdentifier"},{"text":", ","kind":"text"},{"text":"Action","kind":"typeIdentifier"},{"text":">) -> ","kind":"text"},{"text":"IfContent","kind":"typeIdentifier"},{"text":", ","kind":"text"},{"text":"else","kind":"externalParam"},{"text":": () -> ","kind":"text"},{"text":"ElseContent","kind":"typeIdentifier"},{"text":")","kind":"text"}],"modules":[{"name":"ComposableArchitecture"}],"symbolKind":"init","roleHeading":"Initializer"},"variants":[{"paths":["\/documentation\/composablearchitecture\/ifletstore\/init(_:state:action:then:else:)"],"traits":[{"interfaceLanguage":"swift"}]}],"hierarchy":{"paths":[["doc:\/\/ComposableArchitecture\/documentation\/ComposableArchitecture","doc:\/\/ComposableArchitecture\/documentation\/ComposableArchitecture\/SwiftUIIntegration","doc:\/\/ComposableArchitecture\/documentation\/ComposableArchitecture\/SwiftUIDeprecations","doc:\/\/ComposableArchitecture\/documentation\/ComposableArchitecture\/IfLetStore"]]},"schemaVersion":{"minor":3,"major":0,"patch":0},"references":{"doc://ComposableArchitecture/documentation/ComposableArchitecture/IfLetStore":{"navigatorTitle":[{"text":"IfLetStore","kind":"identifier"}],"identifier":"doc:\/\/ComposableArchitecture\/documentation\/ComposableArchitecture\/IfLetStore","url":"\/documentation\/composablearchitecture\/ifletstore","kind":"symbol","role":"symbol","fragments":[{"text":"struct","kind":"keyword"},{"text":" ","kind":"text"},{"text":"IfLetStore","kind":"identifier"}],"deprecated":true,"type":"topic","title":"IfLetStore","abstract":[{"text":"A view that safely unwraps a store of optional state in order to show one of two views.","type":"text"}]},"doc://ComposableArchitecture/documentation/ComposableArchitecture/SwiftUIIntegration":{"url":"\/documentation\/composablearchitecture\/swiftuiintegration","type":"topic","role":"collectionGroup","title":"SwiftUI Integration","abstract":[{"type":"text","text":"Integrating the Composable Architecture into a SwiftUI application."}],"kind":"article","identifier":"doc:\/\/ComposableArchitecture\/documentation\/ComposableArchitecture\/SwiftUIIntegration"},"doc://ComposableArchitecture/documentation/ComposableArchitecture":{"title":"ComposableArchitecture","type":"topic","abstract":[{"type":"text","text":"The Composable Architecture (TCA, for short) is a library for building applications in a consistent"},{"type":"text","text":" "},{"type":"text","text":"and understandable way, with composition, testing, and ergonomics in mind. It can be used in"},{"type":"text","text":" "},{"type":"text","text":"SwiftUI, UIKit, and more, and on any Apple platform (iOS, macOS, tvOS, and watchOS)."}],"kind":"symbol","url":"\/documentation\/composablearchitecture","identifier":"doc:\/\/ComposableArchitecture\/documentation\/ComposableArchitecture","role":"collection"},"doc://ComposableArchitecture/documentation/ComposableArchitecture/IfLetStore/init(_:state:action:then:else:)":{"fragments":[{"kind":"identifier","text":"init"},{"kind":"text","text":"<"},{"kind":"genericParameter","text":"DestinationState"},{"kind":"text","text":", "},{"kind":"genericParameter","text":"DestinationAction"},{"kind":"text","text":", "},{"kind":"genericParameter","text":"IfContent"},{"kind":"text","text":", "},{"kind":"genericParameter","text":"ElseContent"},{"kind":"text","text":">("},{"preciseIdentifier":"s:22ComposableArchitecture5StoreC","kind":"typeIdentifier","text":"Store"},{"kind":"text","text":"<"},{"preciseIdentifier":"s:22ComposableArchitecture17PresentationStateV","kind":"typeIdentifier","text":"PresentationState"},{"kind":"text","text":"<"},{"kind":"typeIdentifier","text":"DestinationState"},{"kind":"text","text":">, "},{"preciseIdentifier":"s:22ComposableArchitecture18PresentationActionO","kind":"typeIdentifier","text":"PresentationAction"},{"kind":"text","text":"<"},{"kind":"typeIdentifier","text":"DestinationAction"},{"kind":"text","text":">>, "},{"kind":"externalParam","text":"state"},{"kind":"text","text":": ("},{"kind":"typeIdentifier","text":"DestinationState"},{"kind":"text","text":") -> "},{"kind":"typeIdentifier","text":"State"},{"kind":"text","text":"?, "},{"kind":"externalParam","text":"action"},{"kind":"text","text":": ("},{"kind":"typeIdentifier","text":"Action"},{"kind":"text","text":") -> "},{"kind":"typeIdentifier","text":"DestinationAction"},{"kind":"text","text":", "},{"kind":"externalParam","text":"then"},{"kind":"text","text":": ("},{"preciseIdentifier":"s:22ComposableArchitecture5StoreC","kind":"typeIdentifier","text":"Store"},{"kind":"text","text":"<"},{"kind":"typeIdentifier","text":"State"},{"kind":"text","text":", "},{"kind":"typeIdentifier","text":"Action"},{"kind":"text","text":">) -> "},{"kind":"typeIdentifier","text":"IfContent"},{"kind":"text","text":", "},{"kind":"externalParam","text":"else"},{"kind":"text","text":": () -> "},{"kind":"typeIdentifier","text":"ElseContent"},{"kind":"text","text":")"}],"type":"topic","kind":"symbol","role":"symbol","identifier":"doc:\/\/ComposableArchitecture\/documentation\/ComposableArchitecture\/IfLetStore\/init(_:state:action:then:else:)","abstract":[{"text":"Initializes an ","type":"text"},{"identifier":"doc:\/\/ComposableArchitecture\/documentation\/ComposableArchitecture\/IfLetStore","type":"reference","isActive":true},{"text":" view that computes content depending on if a store of","type":"text"},{"text":" ","type":"text"},{"identifier":"doc:\/\/ComposableArchitecture\/documentation\/ComposableArchitecture\/PresentationState","type":"reference","isActive":true},{"text":" and ","type":"text"},{"identifier":"doc:\/\/ComposableArchitecture\/documentation\/ComposableArchitecture\/PresentationAction","type":"reference","isActive":true},{"text":" is ","type":"text"},{"type":"codeVoice","code":"nil"},{"text":" or non-","type":"text"},{"type":"codeVoice","code":"nil"},{"text":" and state can further","type":"text"},{"text":" ","type":"text"},{"text":"be extracted from the destination state, ","type":"text"},{"type":"emphasis","inlineContent":[{"type":"text","text":"e.g."}]},{"text":" it matches a particular case of an enum.","type":"text"}],"title":"init(_:state:action:then:else:)","url":"\/documentation\/composablearchitecture\/ifletstore\/init(_:state:action:then:else:)","deprecated":true},"doc://ComposableArchitecture/documentation/ComposableArchitecture/PresentationAction":{"type":"topic","abstract":[{"type":"text","text":"A wrapper type for actions that can be presented."}],"kind":"symbol","url":"\/documentation\/composablearchitecture\/presentationaction","identifier":"doc:\/\/ComposableArchitecture\/documentation\/ComposableArchitecture\/PresentationAction","role":"symbol","title":"PresentationAction","fragments":[{"kind":"keyword","text":"enum"},{"kind":"text","text":" "},{"kind":"identifier","text":"PresentationAction"}],"navigatorTitle":[{"kind":"identifier","text":"PresentationAction"}]},"doc://ComposableArchitecture/documentation/ComposableArchitecture/PresentationState":{"abstract":[{"text":"A property wrapper for state that can be presented.","type":"text"}],"role":"symbol","title":"PresentationState","kind":"symbol","identifier":"doc:\/\/ComposableArchitecture\/documentation\/ComposableArchitecture\/PresentationState","type":"topic","fragments":[{"text":"struct","kind":"keyword"},{"text":" ","kind":"text"},{"text":"PresentationState","kind":"identifier"}],"navigatorTitle":[{"text":"PresentationState","kind":"identifier"}],"url":"\/documentation\/composablearchitecture\/presentationstate"},"doc://ComposableArchitecture/documentation/ComposableArchitecture/Store":{"url":"\/documentation\/composablearchitecture\/store","type":"topic","abstract":[{"text":"A store represents the runtime that powers the application. It is the object that you will pass","type":"text"},{"text":" ","type":"text"},{"text":"around to views that need to interact with the application.","type":"text"}],"fragments":[{"text":"class","kind":"keyword"},{"text":" ","kind":"text"},{"text":"Store","kind":"identifier"}],"title":"Store","kind":"symbol","role":"symbol","navigatorTitle":[{"text":"Store","kind":"identifier"}],"identifier":"doc:\/\/ComposableArchitecture\/documentation\/ComposableArchitecture\/Store"},"doc://ComposableArchitecture/documentation/ComposableArchitecture/SwiftUIDeprecations":{"title":"Deprecations","kind":"article","role":"collectionGroup","url":"\/documentation\/composablearchitecture\/swiftuideprecations","type":"topic","abstract":[{"text":"Review unsupported SwiftUI APIs and their replacements.","type":"text"}],"identifier":"doc:\/\/ComposableArchitecture\/documentation\/ComposableArchitecture\/SwiftUIDeprecations"}}}